Metadata-Version: 2.1
Name: therapist
Version: 2.2.0
Summary: A lint suite runner with Git-aware capabilities and a smart pre-commit hook.
Home-page: https://github.com/rehandalal/therapist
Author: Rehan Dalal
Author-email: rehan@meet-rehan.com
License: Mozilla Public License Version 2.0
Platform: any
Classifier: Development Status :: 5 - Production/Stable
Classifier: Environment :: Console
Classifier: Intended Audience :: Developers
Classifier: License :: OSI Approved :: Mozilla Public License 2.0 (MPL 2.0)
Classifier: Natural Language :: English
Classifier: Operating System :: MacOS
Classifier: Operating System :: Unix
Classifier: Programming Language :: Python
Classifier: Programming Language :: Python :: 3.6
Classifier: Programming Language :: Python :: 3.7
Classifier: Programming Language :: Python :: 3.8
Classifier: Programming Language :: Python :: 3.9
Classifier: Topic :: Software Development :: Build Tools
Classifier: Topic :: Software Development :: Quality Assurance
Classifier: Topic :: Software Development :: Testing
License-File: LICENSE
Requires-Dist: click
Requires-Dist: colorama
Requires-Dist: pathspec
Requires-Dist: PyYAML
